maliang/media/__init__.py
maliang/media/icons.py
maliang/media/main.py
maliang_media-1.1.3.dist-info/LICENSE.txt
maliang_media-1.1.3.dist-info/METADATA
maliang_media-1.1.3.dist-info/WHEEL
maliang_media-1.1.3.dist-info/top_level.txt
maliang_media-1.1.3.dist-info/RECORD
