Metadata-Version: 2.2
Name: maliang-media
Version: 1.1.3
Summary: Extension package for maliang to matplotlib
Author-email: Xiaokang2022 <2951256653@qq.com>
Maintainer-email: Xiaokang2022 <2951256653@qq.com>
License: MIT License
Project-URL: Bug tracker, https://github.com/Xiaokang2022/tkintertools-media/issues
Project-URL: Source code, https://github.com/Xiaokang2022/tkintertools-media
Keywords: tkinter,maliang,media,cross-platform,themed,video
Classifier: Programming Language :: Python :: 3
Classifier: License :: OSI Approved :: MIT License
Classifier: Operating System :: Microsoft :: Windows
Classifier: Operating System :: POSIX :: Linux
Classifier: Operating System :: MacOS
Classifier: Intended Audience :: Developers
Classifier: Typing :: Typed
Requires-Python: >=3.10
License-File: LICENSE.txt
Requires-Dist: typing-extensions
Requires-Dist: maliang>=3.0.0rc6
Requires-Dist: pillow>=10.0.0
Requires-Dist: ffpyplayer>=4.5.0
